easyjax/__init__.py
easyjax/metrics.py
easyjax/ml.py
easyjax-0.1.3.dist-info/WHEEL
easyjax-0.1.3.dist-info/METADATA
easyjax-0.1.3.dist-info/RECORD
