Metadata-Version: 2.1
Name: easyjax
Version: 0.1.3
Summary: Facilitates machine learning development for JAX.
Home-page: https://github.com/rosikand/easyjax
Keywords: python,machine-learning,jax
Author: Rohan Sikand
Author-email: rsikand29@gmail.com
Requires-Python: >=3.8,<4.0
Classifier: Programming Language :: Python :: 3
Classifier: Programming Language :: Python :: 3.8
Classifier: Programming Language :: Python :: 3.9
Classifier: Programming Language :: Python :: 3.10
Classifier: Programming Language :: Python :: 3.11
Requires-Dist: jax (==0.3.25)
